{
  "entity_field_id": 480,
  "entity_field_name": "definition",
  "entity_field_key": "DEFINITION",
  "field_label": "流程定义(JSON)",
  "field_label_cn": "流程定义(JSON)",
  "field_label_en": "definition",
  "field_label_jp": "流程定义(JSON)",
  "entity_id": 29,
  "source_type": "database_design",
  "entity_name": "审批流程表",
  "table_name": "approval_workflows",
  "field_name": "definition",
  "field_name_cn": "流程定义(JSON)",
  "field_type": "JSONObject",
  "java_type": "JSONObject",
  "db_type": "JSONB",
  "physical_type": "JSONB",
  "length": 0,
  "max_length": null,
  "is_primary_key": "N",
  "is_required": "N",
  "is_not_null": "N",
  "is_unique": "N",
  "default_value": "",
  "description": "流程定义(JSON)",
  "logical_description": "流程定义(JSON)",
  "version": "1.0",
  "is_locked": "N",
  "in_table": "Y",
  "in_detail": "Y",
  "in_edit": "Y",
  "in_search": "N",
  "in_create": "Y"
}