{
  "entity_field_id": 493,
  "entity_field_name": "step_number",
  "entity_field_key": "STEP_NUMBER",
  "field_label": "step_number",
  "field_label_cn": "step_number",
  "field_label_en": "step_number",
  "field_label_jp": "step_number",
  "entity_id": 30,
  "source_type": "database_design",
  "entity_name": "审批任务表",
  "table_name": "approval_tasks",
  "field_name": "step_number",
  "field_name_cn": "step_number",
  "field_type": "Integer",
  "java_type": "Integer",
  "db_type": "INTEGER",
  "physical_type": "INTEGER",
  "length": 0,
  "max_length": null,
  "is_primary_key": "N",
  "is_required": "N",
  "is_not_null": "N",
  "is_unique": "N",
  "default_value": "",
  "description": "step_number",
  "logical_description": "step_number",
  "version": "1.0",
  "is_locked": "N",
  "in_table": "Y",
  "in_detail": "Y",
  "in_edit": "Y",
  "in_search": "N",
  "in_create": "Y"
}