{
  "entity_field_id": 129,
  "entity_field_name": "title",
  "entity_field_key": "TITLE",
  "field_label": "title",
  "field_label_cn": "title",
  "field_label_en": "title",
  "field_label_jp": "title",
  "entity_id": 10,
  "source_type": "database_design",
  "entity_name": "项目需求表",
  "table_name": "project_requirements",
  "field_name": "title",
  "field_name_cn": "title",
  "field_type": "String",
  "java_type": "String",
  "db_type": "VARCHAR",
  "physical_type": "VARCHAR",
  "length": 200,
  "max_length": 200,
  "is_primary_key": "N",
  "is_required": "N",
  "is_not_null": "N",
  "is_unique": "N",
  "default_value": "",
  "description": "title",
  "logical_description": "title",
  "version": "1.0",
  "is_locked": "N",
  "in_table": "Y",
  "in_detail": "Y",
  "in_edit": "Y",
  "in_search": "Y",
  "in_create": "Y"
}